LICENSE
MANIFEST.in
README
rel_imp.py
setup.py
rel_imp.egg-info/PKG-INFO
rel_imp.egg-info/SOURCES.txt
rel_imp.egg-info/dependency_links.txt
rel_imp.egg-info/top_level.txt