Metadata-Version: 1.0
Name: rel-imp
Version: 0.2.8
Summary: Enable explicit relative imports in __main__ module.
Home-page: https://github.com/joaduo/rel_imp
Author: Joaquin Duo
Author-email: joaduo@gmail.com
License: MIT
Keywords: explicit,relative,import
Platform: UNKNOWN
